forcha/__init__.py
forcha/components/archiver/archive_manager.py
forcha/components/evaluator/alpha_evaluator.py
forcha/components/evaluator/evaluation_manager.py
forcha/components/evaluator/loo_evaluator.py
forcha/components/evaluator/parallel/parallel_alpha_evaluator.py
forcha/components/evaluator/parallel/parallel_loo_evaluator.py
forcha/components/evaluator/parallel/parallel_manager.py
forcha/components/evaluator/parallel/parallel_shapley_evaluator.py
forcha/components/evaluator/shapley_evaluator.py
forcha/components/nodes/federated_node.py
forcha/components/orchestrator/evaluator_orchestrator.py
forcha/components/orchestrator/fedopt_orchestrator.py
forcha/components/orchestrator/generic_orchestrator.py
forcha/components/settings/adjustive_settings.py
forcha/components/settings/evaluator_settings.py
forcha/components/settings/fedopt_settings.py
forcha/components/settings/settings.py
forcha/exceptions/evaluatorexception.py
forcha/exceptions/modelexception.py
forcha/exceptions/settingexception.py
forcha/models/federated_model.py
forcha/models/templates/cifar10.py
forcha/models/templates/fmnist.py
forcha/models/templates/mnist.py
forcha/utils/computations.py
forcha/utils/csv_handlers.py
forcha/utils/custom_transformations.py
forcha/utils/debugger.py
forcha/utils/handlers.py
forcha/utils/helpers.py
forcha/utils/loggers.py
forcha/utils/optimizers.py
forcha/utils/orchestrations.py
forcha/utils/showcase.py
forcha-0.2.6.dist-info/METADATA
forcha-0.2.6.dist-info/WHEEL
forcha-0.2.6.dist-info/RECORD
