Metadata-Version: 2.1
Name: forcha
Version: 0.2.6
Summary: 
Home-page: https://github.com/Scolpe/forcha
License: MIT
Author: Maciej Zuziak
Author-email: maciejkrzysztof.zuziak@isti.cnr.it
Requires-Python: >=3.09,<4.0
Classifier: License :: OSI Approved :: MIT License
Classifier: Programming Language :: Python :: 3
Classifier: Programming Language :: Python :: 3.9
Classifier: Programming Language :: Python :: 3.10
Classifier: Programming Language :: Python :: 3.11
Requires-Dist: datasets (>=1.0.1)
Requires-Dist: matplotlib (>=3.7.1)
Requires-Dist: numpy (>=1.26.0)
Requires-Dist: scikit-learn (>=1.2.0)
Requires-Dist: timm (>=0.9)
Requires-Dist: torch (>=2.0.0)
Requires-Dist: torchaudio (>=2.0.2)
Requires-Dist: torchvision (>=0.15.1)
Project-URL: Repository, https://github.com/Scolpe/forcha
